[
  {
    "full_name": "microsoft/playwright-dotnet",
    "stargazers_count": 2396,
    "open_issues_count": 45,
    "forks_count": 232
  },
  {
    "full_name": "MicrosoftDocs/edge-developer",
    "stargazers_count": 378,
    "open_issues_count": 31,
    "forks_count": 506
  },
  {
    "full_name": "microsoft/playwright",
    "stargazers_count": 64669,
    "open_issues_count": 722,
    "forks_count": 3520
  },
  {
    "full_name": "puppeteer/puppeteer",
    "stargazers_count": 87928,
    "open_issues_count": 272,
    "forks_count": 9044
  },
  {
    "full_name": "open-sauced/open-sauced",
    "stargazers_count": 928,
    "open_issues_count": 0,
    "forks_count": 948
  }
]