[
  {
    "full_name": "microsoft/playwright-dotnet",
    "stargazers_count": 1747,
    "open_issues_count": 39,
    "forks_count": 161
  },
  {
    "full_name": "MicrosoftDocs/edge-developer",
    "stargazers_count": 281,
    "open_issues_count": 30,
    "forks_count": 448
  },
  {
    "full_name": "microsoft/playwright",
    "stargazers_count": 46056,
    "open_issues_count": 717,
    "forks_count": 2245
  },
  {
    "full_name": "puppeteer/puppeteer",
    "stargazers_count": 81339,
    "open_issues_count": 254,
    "forks_count": 8753
  },
  {
    "full_name": "open-sauced/open-sauced",
    "stargazers_count": 824,
    "open_issues_count": 9,
    "forks_count": 477
  }
]